{"seeds": [{"seed": 0, "data": {"tasks": [{"emptyregion": true, "Fa11": "2", "Fa12": "2", "Fa13": "2", "Fa21": "2", "Fa22": "-2", "Fa23": "1", "Fa31": "1", "Fa32": "1", "Fa33": "-1", "Fb1": "-19", "Fb2": "17", "Fb3": "14", "Fc1": "2", "Fc2": "3", "Fc3": "3", "Fd": "-7", "x1": "x_1", "x2": "t_2", "x3": "t_3", "t1": "t_1", "t2": "x_2", "t3": "x_3", "a11": "16", "a12": "4", "a13": "6", "a21": "-3", "a22": "-1", "a23": "-1", "a31": "-4", "a32": "-1", "a33": "-2", "b1": "133", "b2": "-31", "b3": "-45", "c1": "23", "c2": "6", "c3": "9", "d": "221", "objectivefunction": "23 \\, x_{1} + 6 \\, x_{2} + 9 \\, x_{3} - 221", "row1": "16 \\, x_{1} + 4 \\, x_{2} + 6 \\, x_{3}", "row2": "-3 \\, x_{1} - x_{2} - x_{3}", "row3": "-4 \\, x_{1} - x_{2} - 2 \\, x_{3}", "x1value": "0", "x2value": "17", "x3value": "14", "optimalsolution": "7"}, {"emptyregion": false, "Fa11": "\\frac{1}{2}", "Fa12": "-\\frac{7}{6}", "Fa13": "\\frac{5}{6}", "Fa21": "-\\frac{1}{2}", "Fa22": "\\frac{7}{6}", "Fa23": "\\frac{1}{6}", "Fa31": "\\frac{1}{2}", "Fa32": "-\\frac{1}{2}", "Fa33": "-\\frac{1}{2}", "Fb1": "\\frac{11}{2}", "Fb2": "\\frac{1}{2}", "Fb3": "\\frac{3}{2}", "Fc1": "\\frac{5}{2}", "Fc2": "-\\frac{17}{6}", "Fc3": "-\\frac{11}{6}", "Fd": "-\\frac{27}{2}", "x1": "t_2", "x2": "x_2", "x3": "t_3", "t1": "t_1", "t2": "x_1", "t3": "x_3", "a11": "4", "a12": "2", "a13": "3", "a21": "-3", "a22": "-3", "a23": "-1", "a31": "-3", "a32": "-2", "a33": "-3", "b1": "12", "b2": "-3", "b3": "-6", "c1": "2", "c2": "1", "c3": "-3", "d": "-17", "objectivefunction": "2 \\, x_{1} + x_{2} - 3 \\, x_{3} + 17", "row1": "4 \\, x_{1} + 2 \\, x_{2} + 3 \\, x_{3}", "row2": "-3 \\, x_{1} - 3 \\, x_{2} - x_{3}", "row3": "-3 \\, x_{1} - 2 \\, x_{2} - 3 \\, x_{3}", "x1value": "\\frac{1}{2}", "x2value": "0", "x3value": "\\frac{3}{2}", "optimalsolution": "\\frac{27}{2}"}], "__seed__": "0000"}}, {"seed": 1, "data": {"tasks": [{"emptyregion": false, "Fa11": "\\frac{3}{11}", "Fa12": "\\frac{1}{33}", "Fa13": "-\\frac{31}{33}", "Fa21": "-\\frac{5}{11}", "Fa22": "\\frac{2}{33}", "Fa23": "\\frac{70}{33}", "Fa31": "\\frac{2}{11}", "Fa32": "-\\frac{1}{11}", "Fa33": "-\\frac{2}{11}", "Fb1": "\\frac{38}{11}", "Fb2": "\\frac{10}{11}", "Fb3": "\\frac{18}{11}", "Fc1": "\\frac{18}{11}", "Fc2": "-\\frac{5}{33}", "Fc3": "-\\frac{208}{33}", "Fd": "-\\frac{168}{11}", "x1": "t_2", "x2": "t_3", "x3": "x_3", "t1": "t_1", "t2": "x_1", "t3": "x_2", "a11": "1", "a12": "1", "a13": "1", "a21": "-3", "a22": "-2", "a23": "-6", "a31": "-6", "a32": "-15", "a33": "-10", "b1": "6", "b2": "-6", "b3": "-30", "c1": "4", "c2": "1", "c3": "2", "d": "-10", "objectivefunction": "4 \\, x_{1} + x_{2} + 2 \\, x_{3} + 10", "row1": "x_{1} + x_{2} + x_{3}", "row2": "-3 \\, x_{1} - 2 \\, x_{2} - 6 \\, x_{3}", "row3": "-6 \\, x_{1} - 15 \\, x_{2} - 10 \\, x_{3}", "x1value": "\\frac{10}{11}", "x2value": "\\frac{18}{11}", "x3value": "0", "optimalsolution": "\\frac{168}{11}"}, {"emptyregion": true, "Fa11": "2", "Fa12": "1", "Fa13": "2", "Fa21": "-2", "Fa22": "1", "Fa23": "1", "Fa31": "1", "Fa32": "-1", "Fa33": "2", "Fb1": "-20", "Fb2": "17", "Fb3": "20", "Fc1": "-4", "Fc2": "1", "Fc3": "2", "Fd": "-2", "x1": "t_2", "x2": "t_3", "x3": "x_3", "t1": "t_1", "t2": "x_1", "t3": "x_2", "a11": "3", "a12": "4", "a13": "13", "a21": "-1", "a22": "-1", "a23": "-3", "a31": "-1", "a32": "-2", "a33": "-5", "b1": "111", "b2": "-37", "b3": "-57", "c1": "-3", "c2": "-2", "c3": "-5", "d": "-93", "objectivefunction": "-3 \\, x_{1} - 2 \\, x_{2} - 5 \\, x_{3} + 93", "row1": "3 \\, x_{1} + 4 \\, x_{2} + 13 \\, x_{3}", "row2": "-x_{1} - x_{2} - 3 \\, x_{3}", "row3": "-x_{1} - 2 \\, x_{2} - 5 \\, x_{3}", "x1value": "17", "x2value": "20", "x3value": "0", "optimalsolution": "2"}], "__seed__": "0001"}}, {"seed": 2, "data": {"tasks": [{"emptyregion": false, "Fa11": "\\frac{15}{7}", "Fa12": "\\frac{5}{7}", "Fa13": "-4", "Fa21": "-\\frac{4}{7}", "Fa22": "\\frac{1}{7}", "Fa23": "2", "Fa31": "\\frac{1}{7}", "Fa32": "-\\frac{2}{7}", "Fa33": "0", "Fb1": "\\frac{130}{7}", "Fb2": "\\frac{12}{7}", "Fb3": "\\frac{4}{7}", "Fc1": "\\frac{13}{7}", "Fc2": "-\\frac{12}{7}", "Fc3": "-1", "Fd": "\\frac{10}{7}", "x1": "t_2", "x2": "t_3", "x3": "x_3", "t1": "t_1", "t2": "x_1", "t3": "x_2", "a11": "5", "a12": "5", "a13": "6", "a21": "-2", "a22": "-1", "a23": "-4", "a31": "-1", "a32": "-4", "a33": "-2", "b1": "30", "b2": "-4", "b3": "-4", "c1": "2", "c2": "-5", "c3": "3", "d": "2", "objectivefunction": "2 \\, x_{1} - 5 \\, x_{2} + 3 \\, x_{3} - 2", "row1": "5 \\, x_{1} + 5 \\, x_{2} + 6 \\, x_{3}", "row2": "-2 \\, x_{1} - x_{2} - 4 \\, x_{3}", "row3": "-x_{1} - 4 \\, x_{2} - 2 \\, x_{3}", "x1value": "\\frac{12}{7}", "x2value": "\\frac{4}{7}", "x3value": "0", "optimalsolution": "-\\frac{10}{7}"}, {"emptyregion": true, "Fa11": "1", "Fa12": "2", "Fa13": "1", "Fa21": "\\frac{1}{2}", "Fa22": "1", "Fa23": "-1", "Fa31": "-1", "Fa32": "1", "Fa33": "1", "Fb1": "-34", "Fb2": "17", "Fb3": "14", "Fc1": "1", "Fc2": "6", "Fc3": "4", "Fd": "-38", "x1": "t_3", "x2": "x_2", "x3": "t_2", "t1": "t_1", "t2": "x_3", "t3": "x_1", "a11": "3", "a12": "9", "a13": "4", "a21": "-1", "a22": "-3", "a23": "-2", "a31": "-2", "a32": "-4", "a33": "-2", "b1": "76", "b2": "-48", "b3": "-62", "c1": "6", "c2": "22", "c3": "10", "d": "216", "objectivefunction": "6 \\, x_{1} + 22 \\, x_{2} + 10 \\, x_{3} - 216", "row1": "3 \\, x_{1} + 9 \\, x_{2} + 4 \\, x_{3}", "row2": "-x_{1} - 3 \\, x_{2} - 2 \\, x_{3}", "row3": "-2 \\, x_{1} - 4 \\, x_{2} - 2 \\, x_{3}", "x1value": "14", "x2value": "0", "x3value": "17", "optimalsolution": "38"}], "__seed__": "0002"}}, {"seed": 3, "data": {"tasks": [{"emptyregion": false, "Fa11": "\\frac{9}{13}", "Fa12": "\\frac{14}{13}", "Fa13": "-\\frac{9}{13}", "Fa21": "-\\frac{4}{13}", "Fa22": "\\frac{1}{13}", "Fa23": "\\frac{4}{13}", "Fa31": "\\frac{3}{13}", "Fa32": "-\\frac{4}{13}", "Fa33": "\\frac{10}{13}", "Fb1": "\\frac{186}{13}", "Fb2": "\\frac{4}{13}", "Fb3": "\\frac{36}{13}", "Fc1": "\\frac{14}{13}", "Fc2": "\\frac{3}{13}", "Fc3": "-\\frac{1}{13}", "Fd": "-\\frac{183}{13}", "x1": "t_2", "x2": "t_3", "x3": "x_3", "t1": "t_1", "t2": "x_1", "t3": "x_2", "a11": "6", "a12": "5", "a13": "5", "a21": "-4", "a22": "-1", "a23": "-2", "a31": "-3", "a32": "-4", "a33": "-4", "b1": "30", "b2": "-4", "b3": "-12", "c1": "5", "c2": "2", "c3": "3", "d": "-7", "objectivefunction": "5 \\, x_{1} + 2 \\, x_{2} + 3 \\, x_{3} + 7", "row1": "6 \\, x_{1} + 5 \\, x_{2} + 5 \\, x_{3}", "row2": "-4 \\, x_{1} - x_{2} - 2 \\, x_{3}", "row3": "-3 \\, x_{1} - 4 \\, x_{2} - 4 \\, x_{3}", "x1value": "\\frac{4}{13}", "x2value": "\\frac{36}{13}", "x3value": "0", "optimalsolution": "\\frac{183}{13}"}, {"emptyregion": true, "Fa11": "1", "Fa12": "2", "Fa13": "1", "Fa21": "-2", "Fa22": "1", "Fa23": "2", "Fa31": "1", "Fa32": "-1", "Fa33": "1", "Fb1": "-20", "Fb2": "15", "Fb3": "16", "Fc1": "1", "Fc2": "4", "Fc3": "4", "Fd": "-15", "x1": "t_2", "x2": "t_3", "x3": "x_3", "t1": "t_1", "t2": "x_1", "t3": "x_2", "a11": "3", "a12": "5", "a13": "12", "a21": "-1", "a22": "-1", "a23": "-3", "a31": "-1", "a32": "-2", "a33": "-4", "b1": "105", "b2": "-31", "b3": "-47", "c1": "5", "c2": "9", "c3": "23", "d": "204", "objectivefunction": "5 \\, x_{1} + 9 \\, x_{2} + 23 \\, x_{3} - 204", "row1": "3 \\, x_{1} + 5 \\, x_{2} + 12 \\, x_{3}", "row2": "-x_{1} - x_{2} - 3 \\, x_{3}", "row3": "-x_{1} - 2 \\, x_{2} - 4 \\, x_{3}", "x1value": "15", "x2value": "16", "x3value": "0", "optimalsolution": "15"}], "__seed__": "0003"}}, {"seed": 4, "data": {"tasks": [{"emptyregion": false, "Fa11": "-\\frac{43}{15}", "Fa12": "\\frac{14}{5}", "Fa13": "\\frac{4}{15}", "Fa21": "\\frac{8}{5}", "Fa22": "-\\frac{2}{5}", "Fa23": "\\frac{1}{5}", "Fa31": "-\\frac{2}{15}", "Fa32": "\\frac{1}{5}", "Fa33": "-\\frac{4}{15}", "Fb1": "\\frac{116}{5}", "Fb2": "\\frac{12}{5}", "Fb3": "\\frac{4}{5}", "Fc1": "-\\frac{26}{15}", "Fc2": "\\frac{3}{5}", "Fc3": "\\frac{8}{15}", "Fd": "-\\frac{73}{5}", "x1": "x_1", "x2": "t_2", "x3": "t_3", "t1": "t_1", "t2": "x_2", "t3": "x_3", "a11": "15", "a12": "12", "a13": "10", "a21": "-6", "a22": "-4", "a23": "-3", "a31": "-4", "a32": "-3", "a33": "-6", "b1": "60", "b2": "-12", "b3": "-12", "c1": "4", "c2": "4", "c3": "5", "d": "-1", "objectivefunction": "4 \\, x_{1} + 4 \\, x_{2} + 5 \\, x_{3} + 1", "row1": "15 \\, x_{1} + 12 \\, x_{2} + 10 \\, x_{3}", "row2": "-6 \\, x_{1} - 4 \\, x_{2} - 3 \\, x_{3}", "row3": "-4 \\, x_{1} - 3 \\, x_{2} - 6 \\, x_{3}", "x1value": "0", "x2value": "\\frac{12}{5}", "x3value": "\\frac{4}{5}", "optimalsolution": "\\frac{73}{5}"}, {"emptyregion": true, "Fa11": "1", "Fa12": "1", "Fa13": "6", "Fa21": "-\\frac{2}{3}", "Fa22": "\\frac{1}{3}", "Fa23": "1", "Fa31": "\\frac{1}{3}", "Fa32": "-\\frac{2}{3}", "Fa33": "2", "Fb1": "-36", "Fb2": "17", "Fb3": "20", "Fc1": "2", "Fc2": "4", "Fc3": "-12", "Fd": "6", "x1": "t_2", "x2": "t_3", "x3": "x_3", "t1": "t_1", "t2": "x_1", "t3": "x_2", "a11": "3", "a12": "3", "a13": "15", "a21": "-2", "a22": "-1", "a23": "-4", "a31": "-1", "a32": "-2", "a33": "-5", "b1": "75", "b2": "-54", "b3": "-57", "c1": "8", "c2": "10", "c3": "16", "d": "342", "objectivefunction": "8 \\, x_{1} + 10 \\, x_{2} + 16 \\, x_{3} - 342", "row1": "3 \\, x_{1} + 3 \\, x_{2} + 15 \\, x_{3}", "row2": "-2 \\, x_{1} - x_{2} - 4 \\, x_{3}", "row3": "-x_{1} - 2 \\, x_{2} - 5 \\, x_{3}", "x1value": "17", "x2value": "20", "x3value": "0", "optimalsolution": "-6"}], "__seed__": "0004"}}, {"seed": 5, "data": {"tasks": [{"emptyregion": true, "Fa11": "2", "Fa12": "2", "Fa13": "4", "Fa21": "1", "Fa22": "-1", "Fa23": "1", "Fa31": "-1", "Fa32": "\\frac{1}{2}", "Fa33": "2", "Fb1": "-38", "Fb2": "12", "Fb3": "14", "Fc1": "2", "Fc2": "4", "Fc3": "10", "Fd": "-8", "x1": "t_3", "x2": "t_2", "x3": "x_3", "t1": "t_1", "t2": "x_2", "t3": "x_1", "a11": "8", "a12": "6", "a13": "26", "a21": "-2", "a22": "-2", "a23": "-6", "a31": "-2", "a32": "-1", "a33": "-5", "b1": "146", "b2": "-52", "b3": "-40", "c1": "12", "c2": "10", "c3": "44", "d": "280", "objectivefunction": "12 \\, x_{1} + 10 \\, x_{2} + 44 \\, x_{3} - 280", "row1": "8 \\, x_{1} + 6 \\, x_{2} + 26 \\, x_{3}", "row2": "-2 \\, x_{1} - 2 \\, x_{2} - 6 \\, x_{3}", "row3": "-2 \\, x_{1} - x_{2} - 5 \\, x_{3}", "x1value": "14", "x2value": "12", "x3value": "0", "optimalsolution": "8"}, {"emptyregion": false, "Fa11": "\\frac{7}{4}", "Fa12": "\\frac{1}{4}", "Fa13": "-\\frac{7}{2}", "Fa21": "-\\frac{5}{4}", "Fa22": "\\frac{1}{4}", "Fa23": "\\frac{7}{2}", "Fa31": "\\frac{1}{4}", "Fa32": "-\\frac{1}{4}", "Fa33": "-\\frac{1}{2}", "Fb1": "\\frac{11}{2}", "Fb2": "\\frac{5}{2}", "Fb3": "\\frac{1}{2}", "Fc1": "\\frac{23}{4}", "Fc2": "-\\frac{3}{4}", "Fc3": "-\\frac{29}{2}", "Fd": "-\\frac{67}{2}", "x1": "t_2", "x2": "t_3", "x3": "x_3", "t1": "t_1", "t2": "x_1", "t3": "x_2", "a11": "2", "a12": "3", "a13": "2", "a21": "-1", "a22": "-1", "a23": "-3", "a31": "-1", "a32": "-5", "a33": "-1", "b1": "12", "b2": "-3", "b3": "-5", "c1": "5", "c2": "2", "c3": "2", "d": "-20", "objectivefunction": "5 \\, x_{1} + 2 \\, x_{2} + 2 \\, x_{3} + 20", "row1": "2 \\, x_{1} + 3 \\, x_{2} + 2 \\, x_{3}", "row2": "-x_{1} - x_{2} - 3 \\, x_{3}", "row3": "-x_{1} - 5 \\, x_{2} - x_{3}", "x1value": "\\frac{5}{2}", "x2value": "\\frac{1}{2}", "x3value": "0", "optimalsolution": "\\frac{67}{2}"}], "__seed__": "0005"}}, {"seed": 6, "data": {"tasks": [{"emptyregion": true, "Fa11": "1", "Fa12": "1", "Fa13": "2", "Fa21": "\\frac{1}{2}", "Fa22": "-1", "Fa23": "1", "Fa31": "-1", "Fa32": "1", "Fa33": "1", "Fb1": "-38", "Fb2": "10", "Fb3": "17", "Fc1": "1", "Fc2": "5", "Fc3": "2", "Fd": "2", "x1": "t_3", "x2": "t_2", "x3": "x_3", "t1": "t_1", "t2": "x_2", "t3": "x_1", "a11": "3", "a12": "4", "a13": "9", "a21": "-1", "a22": "-2", "a23": "-3", "a31": "-2", "a32": "-2", "a33": "-4", "b1": "53", "b2": "-37", "b3": "-54", "c1": "7", "c2": "12", "c3": "21", "d": "241", "objectivefunction": "7 \\, x_{1} + 12 \\, x_{2} + 21 \\, x_{3} - 241", "row1": "3 \\, x_{1} + 4 \\, x_{2} + 9 \\, x_{3}", "row2": "-x_{1} - 2 \\, x_{2} - 3 \\, x_{3}", "row3": "-2 \\, x_{1} - 2 \\, x_{2} - 4 \\, x_{3}", "x1value": "17", "x2value": "10", "x3value": "0", "optimalsolution": "-2"}, {"emptyregion": false, "Fa11": "-\\frac{5}{3}", "Fa12": "\\frac{2}{3}", "Fa13": "1", "Fa21": "\\frac{20}{21}", "Fa22": "\\frac{1}{21}", "Fa23": "-\\frac{2}{7}", "Fa31": "\\frac{4}{21}", "Fa32": "-\\frac{4}{21}", "Fa33": "\\frac{1}{7}", "Fb1": "18", "Fb2": "\\frac{4}{7}", "Fb3": "\\frac{12}{7}", "Fc1": "-\\frac{1}{21}", "Fc2": "\\frac{1}{21}", "Fc3": "\\frac{5}{7}", "Fd": "-\\frac{73}{7}", "x1": "x_1", "x2": "t_3", "x3": "t_2", "t1": "t_1", "t2": "x_3", "t3": "x_2", "a11": "5", "a12": "5", "a13": "6", "a21": "-4", "a22": "-1", "a23": "-4", "a31": "-4", "a32": "-6", "a33": "-3", "b1": "30", "b2": "-4", "b3": "-12", "c1": "3", "c2": "1", "c3": "3", "d": "-7", "objectivefunction": "3 \\, x_{1} + x_{2} + 3 \\, x_{3} + 7", "row1": "5 \\, x_{1} + 5 \\, x_{2} + 6 \\, x_{3}", "row2": "-4 \\, x_{1} - x_{2} - 4 \\, x_{3}", "row3": "-4 \\, x_{1} - 6 \\, x_{2} - 3 \\, x_{3}", "x1value": "0", "x2value": "\\frac{12}{7}", "x3value": "\\frac{4}{7}", "optimalsolution": "\\frac{73}{7}"}], "__seed__": "0006"}}, {"seed": 7, "data": {"tasks": [{"emptyregion": false, "Fa11": "\\frac{31}{10}", "Fa12": "\\frac{21}{5}", "Fa13": "\\frac{9}{10}", "Fa21": "\\frac{9}{20}", "Fa22": "-\\frac{3}{5}", "Fa23": "\\frac{1}{20}", "Fa31": "\\frac{1}{10}", "Fa32": "\\frac{1}{5}", "Fa33": "-\\frac{1}{10}", "Fb1": "\\frac{204}{5}", "Fb2": "\\frac{3}{5}", "Fb3": "\\frac{4}{5}", "Fc1": "-\\frac{11}{20}", "Fc2": "\\frac{12}{5}", "Fc3": "\\frac{1}{20}", "Fd": "-\\frac{47}{5}", "x1": "x_1", "x2": "t_2", "x3": "t_3", "t1": "t_1", "t2": "x_2", "t3": "x_3", "a11": "10", "a12": "12", "a13": "15", "a21": "-1", "a22": "-2", "a23": "-1", "a31": "-3", "a32": "-4", "a33": "-12", "b1": "60", "b2": "-2", "b3": "-12", "c1": "2", "c2": "5", "c3": "3", "d": "-4", "objectivefunction": "2 \\, x_{1} + 5 \\, x_{2} + 3 \\, x_{3} + 4", "row1": "10 \\, x_{1} + 12 \\, x_{2} + 15 \\, x_{3}", "row2": "-x_{1} - 2 \\, x_{2} - x_{3}", "row3": "-3 \\, x_{1} - 4 \\, x_{2} - 12 \\, x_{3}", "x1value": "0", "x2value": "\\frac{3}{5}", "x3value": "\\frac{4}{5}", "optimalsolution": "\\frac{47}{5}"}, {"emptyregion": true, "Fa11": "1", "Fa12": "1", "Fa13": "2", "Fa21": "\\frac{1}{2}", "Fa22": "-1", "Fa23": "2", "Fa31": "-1", "Fa32": "1", "Fa33": "2", "Fb1": "-38", "Fb2": "20", "Fb3": "11", "Fc1": "3", "Fc2": "5", "Fc3": "-2", "Fd": "-4", "x1": "t_3", "x2": "t_2", "x3": "x_3", "t1": "t_1", "t2": "x_2", "t3": "x_1", "a11": "3", "a12": "4", "a13": "16", "a21": "-1", "a22": "-2", "a23": "-6", "a31": "-2", "a32": "-2", "a33": "-8", "b1": "75", "b2": "-51", "b3": "-62", "c1": "11", "c2": "16", "c3": "52", "d": "437", "objectivefunction": "11 \\, x_{1} + 16 \\, x_{2} + 52 \\, x_{3} - 437", "row1": "3 \\, x_{1} + 4 \\, x_{2} + 16 \\, x_{3}", "row2": "-x_{1} - 2 \\, x_{2} - 6 \\, x_{3}", "row3": "-2 \\, x_{1} - 2 \\, x_{2} - 8 \\, x_{3}", "x1value": "11", "x2value": "20", "x3value": "0", "optimalsolution": "4"}], "__seed__": "0007"}}, {"seed": 8, "data": {"tasks": [{"emptyregion": false, "Fa11": "\\frac{7}{12}", "Fa12": "\\frac{5}{12}", "Fa13": "\\frac{3}{4}", "Fa21": "\\frac{1}{6}", "Fa22": "\\frac{5}{6}", "Fa23": "-\\frac{1}{2}", "Fa31": "-\\frac{1}{4}", "Fa32": "\\frac{1}{4}", "Fa33": "\\frac{1}{4}", "Fb1": "\\frac{17}{2}", "Fb2": "1", "Fb3": "\\frac{3}{2}", "Fc1": "\\frac{3}{4}", "Fc2": "-\\frac{19}{4}", "Fc3": "\\frac{1}{4}", "Fd": "-\\frac{25}{2}", "x1": "t_3", "x2": "x_2", "x3": "t_2", "t1": "t_1", "t2": "x_3", "t3": "x_1", "a11": "5", "a12": "5", "a13": "4", "a21": "-2", "a22": "-3", "a23": "-3", "a31": "-6", "a32": "-4", "a33": "-3", "b1": "20", "b2": "-6", "b3": "-12", "c1": "5", "c2": "-1", "c3": "3", "d": "-2", "objectivefunction": "5 \\, x_{1} - x_{2} + 3 \\, x_{3} + 2", "row1": "5 \\, x_{1} + 5 \\, x_{2} + 4 \\, x_{3}", "row2": "-2 \\, x_{1} - 3 \\, x_{2} - 3 \\, x_{3}", "row3": "-6 \\, x_{1} - 4 \\, x_{2} - 3 \\, x_{3}", "x1value": "\\frac{3}{2}", "x2value": "0", "x3value": "1", "optimalsolution": "\\frac{25}{2}"}, {"emptyregion": true, "Fa11": "1", "Fa12": "2", "Fa13": "1", "Fa21": "1", "Fa22": "-1", "Fa23": "1", "Fa31": "-2", "Fa32": "1", "Fa33": "1", "Fb1": "-13", "Fb2": "15", "Fb3": "12", "Fc1": "1", "Fc2": "4", "Fc3": "1", "Fd": "-3", "x1": "t_3", "x2": "t_2", "x3": "x_3", "t1": "t_1", "t2": "x_2", "t3": "x_1", "a11": "3", "a12": "5", "a13": "9", "a21": "-1", "a22": "-2", "a23": "-3", "a31": "-1", "a32": "-1", "a33": "-2", "b1": "98", "b2": "-42", "b3": "-27", "c1": "5", "c2": "9", "c3": "15", "d": "192", "objectivefunction": "5 \\, x_{1} + 9 \\, x_{2} + 15 \\, x_{3} - 192", "row1": "3 \\, x_{1} + 5 \\, x_{2} + 9 \\, x_{3}", "row2": "-x_{1} - 2 \\, x_{2} - 3 \\, x_{3}", "row3": "-x_{1} - x_{2} - 2 \\, x_{3}", "x1value": "12", "x2value": "15", "x3value": "0", "optimalsolution": "3"}], "__seed__": "0008"}}, {"seed": 9, "data": {"tasks": [{"emptyregion": false, "Fa11": "\\frac{14}{55}", "Fa12": "\\frac{13}{33}", "Fa13": "\\frac{439}{165}", "Fa21": "\\frac{1}{55}", "Fa22": "-\\frac{1}{11}", "Fa23": "\\frac{17}{55}", "Fa31": "-\\frac{4}{55}", "Fa32": "\\frac{1}{33}", "Fa33": "\\frac{16}{165}", "Fb1": "\\frac{236}{11}", "Fb2": "\\frac{9}{11}", "Fb3": "\\frac{8}{11}", "Fc1": "\\frac{3}{11}", "Fc2": "\\frac{10}{33}", "Fc3": "\\frac{65}{33}", "Fd": "-\\frac{96}{11}", "x1": "t_3", "x2": "t_2", "x3": "x_3", "t1": "t_1", "t2": "x_2", "t3": "x_1", "a11": "5", "a12": "6", "a13": "5", "a21": "-3", "a22": "-12", "a23": "-4", "a31": "-15", "a32": "-5", "a33": "-3", "b1": "30", "b2": "-12", "b3": "-15", "c1": "5", "c2": "5", "c3": "4", "d": "-1", "objectivefunction": "5 \\, x_{1} + 5 \\, x_{2} + 4 \\, x_{3} + 1", "row1": "5 \\, x_{1} + 6 \\, x_{2} + 5 \\, x_{3}", "row2": "-3 \\, x_{1} - 12 \\, x_{2} - 4 \\, x_{3}", "row3": "-15 \\, x_{1} - 5 \\, x_{2} - 3 \\, x_{3}", "x1value": "\\frac{8}{11}", "x2value": "\\frac{9}{11}", "x3value": "0", "optimalsolution": "\\frac{96}{11}"}, {"emptyregion": true, "Fa11": "1", "Fa12": "2", "Fa13": "2", "Fa21": "\\frac{1}{2}", "Fa22": "2", "Fa23": "-1", "Fa31": "-1", "Fa32": "2", "Fa33": "1", "Fb1": "-28", "Fb2": "10", "Fb3": "11", "Fc1": "2", "Fc2": "8", "Fc3": "2", "Fd": "-16", "x1": "t_3", "x2": "x_2", "x3": "t_2", "t1": "t_1", "t2": "x_3", "t3": "x_1", "a11": "4", "a12": "22", "a13": "6", "a21": "-1", "a22": "-6", "a23": "-2", "a31": "-2", "a32": "-8", "a33": "-2", "b1": "76", "b2": "-31", "b3": "-42", "c1": "6", "c2": "36", "c3": "8", "d": "130", "objectivefunction": "6 \\, x_{1} + 36 \\, x_{2} + 8 \\, x_{3} - 130", "row1": "4 \\, x_{1} + 22 \\, x_{2} + 6 \\, x_{3}", "row2": "-x_{1} - 6 \\, x_{2} - 2 \\, x_{3}", "row3": "-2 \\, x_{1} - 8 \\, x_{2} - 2 \\, x_{3}", "x1value": "11", "x2value": "0", "x3value": "10", "optimalsolution": "16"}], "__seed__": "0009"}}, {"seed": 10, "data": {"tasks": [{"emptyregion": false, "Fa11": "\\frac{9}{5}", "Fa12": "\\frac{7}{10}", "Fa13": "\\frac{21}{10}", "Fa21": "\\frac{1}{5}", "Fa22": "-\\frac{1}{5}", "Fa23": "\\frac{2}{5}", "Fa31": "-\\frac{3}{5}", "Fa32": "\\frac{1}{10}", "Fa33": "\\frac{3}{10}", "Fb1": "\\frac{93}{5}", "Fb2": "\\frac{2}{5}", "Fb3": "\\frac{9}{5}", "Fc1": "\\frac{9}{5}", "Fc2": "\\frac{1}{5}", "Fc3": "-\\frac{12}{5}", "Fd": "-\\frac{47}{5}", "x1": "t_3", "x2": "t_2", "x3": "x_3", "t1": "t_1", "t2": "x_2", "t3": "x_1", "a11": "5", "a12": "6", "a13": "6", "a21": "-2", "a22": "-6", "a23": "-3", "a31": "-2", "a32": "-1", "a33": "-1", "b1": "30", "b2": "-6", "b3": "-4", "c1": "4", "c2": "3", "c3": "0", "d": "-1", "objectivefunction": "4 \\, x_{1} + 3 \\, x_{2} + 1", "row1": "5 \\, x_{1} + 6 \\, x_{2} + 6 \\, x_{3}", "row2": "-2 \\, x_{1} - 6 \\, x_{2} - 3 \\, x_{3}", "row3": "-2 \\, x_{1} - x_{2} - x_{3}", "x1value": "\\frac{9}{5}", "x2value": "\\frac{2}{5}", "x3value": "0", "optimalsolution": "\\frac{47}{5}"}, {"emptyregion": true, "Fa11": "6", "Fa12": "1", "Fa13": "1", "Fa21": "1", "Fa22": "\\frac{1}{3}", "Fa23": "-\\frac{2}{3}", "Fa31": "2", "Fa32": "-\\frac{2}{3}", "Fa33": "\\frac{1}{3}", "Fb1": "-54", "Fb2": "10", "Fb3": "17", "Fc1": "6", "Fc2": "3", "Fc3": "5", "Fd": "-48", "x1": "x_1", "x2": "t_3", "x3": "t_2", "t1": "t_1", "t2": "x_3", "t3": "x_2", "a11": "15", "a12": "3", "a13": "3", "a21": "-4", "a22": "-1", "a23": "-2", "a31": "-5", "a32": "-2", "a33": "-1", "b1": "27", "b2": "-37", "b3": "-44", "c1": "41", "c2": "11", "c3": "13", "d": "269", "objectivefunction": "41 \\, x_{1} + 11 \\, x_{2} + 13 \\, x_{3} - 269", "row1": "15 \\, x_{1} + 3 \\, x_{2} + 3 \\, x_{3}", "row2": "-4 \\, x_{1} - x_{2} - 2 \\, x_{3}", "row3": "-5 \\, x_{1} - 2 \\, x_{2} - x_{3}", "x1value": "0", "x2value": "17", "x3value": "10", "optimalsolution": "48"}], "__seed__": "0010"}}, {"seed": 11, "data": {"tasks": [{"emptyregion": false, "Fa11": "\\frac{1}{2}", "Fa12": "0", "Fa13": "\\frac{1}{2}", "Fa21": "\\frac{2}{5}", "Fa22": "\\frac{1}{15}", "Fa23": "-\\frac{2}{3}", "Fa31": "\\frac{1}{10}", "Fa32": "-\\frac{1}{15}", "Fa33": "\\frac{1}{6}", "Fb1": "4", "Fb2": "\\frac{4}{3}", "Fb3": "\\frac{2}{3}", "Fc1": "\\frac{1}{10}", "Fc2": "\\frac{4}{15}", "Fc3": "-\\frac{1}{6}", "Fd": "-\\frac{29}{3}", "x1": "x_1", "x2": "t_3", "x3": "t_2", "t1": "t_1", "t2": "x_3", "t3": "x_2", "a11": "1", "a12": "1", "a13": "1", "a21": "-1", "a22": "-2", "a23": "-2", "a31": "-4", "a32": "-20", "a33": "-5", "b1": "6", "b2": "-4", "b3": "-20", "c1": "1", "c2": "5", "c3": "1", "d": "-5", "objectivefunction": "x_{1} + 5 \\, x_{2} + x_{3} + 5", "row1": "x_{1} + x_{2} + x_{3}", "row2": "-x_{1} - 2 \\, x_{2} - 2 \\, x_{3}", "row3": "-4 \\, x_{1} - 20 \\, x_{2} - 5 \\, x_{3}", "x1value": "0", "x2value": "\\frac{2}{3}", "x3value": "\\frac{4}{3}", "optimalsolution": "\\frac{29}{3}"}, {"emptyregion": true, "Fa11": "2", "Fa12": "6", "Fa13": "1", "Fa21": "\\frac{1}{3}", "Fa22": "2", "Fa23": "-\\frac{2}{3}", "Fa31": "-\\frac{2}{3}", "Fa32": "2", "Fa33": "\\frac{1}{3}", "Fb1": "-45", "Fb2": "18", "Fb3": "16", "Fc1": "-1", "Fc2": "6", "Fc3": "5", "Fd": "0", "x1": "t_3", "x2": "x_2", "x3": "t_2", "t1": "t_1", "t2": "x_3", "t3": "x_1", "a11": "5", "a12": "24", "a13": "4", "a21": "-1", "a22": "-6", "a23": "-2", "a31": "-2", "a32": "-6", "a33": "-1", "b1": "107", "b2": "-52", "b3": "-50", "c1": "3", "c2": "30", "c3": "9", "d": "210", "objectivefunction": "3 \\, x_{1} + 30 \\, x_{2} + 9 \\, x_{3} - 210", "row1": "5 \\, x_{1} + 24 \\, x_{2} + 4 \\, x_{3}", "row2": "-x_{1} - 6 \\, x_{2} - 2 \\, x_{3}", "row3": "-2 \\, x_{1} - 6 \\, x_{2} - x_{3}", "x1value": "16", "x2value": "0", "x3value": "18", "optimalsolution": "0"}], "__seed__": "0011"}}, {"seed": 12, "data": {"tasks": [{"emptyregion": true, "Fa11": "2", "Fa12": "1", "Fa13": "2", "Fa21": "-1", "Fa22": "\\frac{1}{2}", "Fa23": "2", "Fa31": "1", "Fa32": "-1", "Fa33": "1", "Fb1": "-32", "Fb2": "17", "Fb3": "16", "Fc1": "2", "Fc2": "-4", "Fc3": "6", "Fd": "-12", "x1": "t_2", "x2": "t_3", "x3": "x_3", "t1": "t_1", "t2": "x_1", "t3": "x_2", "a11": "6", "a12": "4", "a13": "18", "a21": "-2", "a22": "-1", "a23": "-5", "a31": "-2", "a32": "-2", "a33": "-6", "b1": "134", "b2": "-50", "b3": "-66", "c1": "-4", "c2": "-6", "c3": "-8", "d": "-176", "objectivefunction": "-4 \\, x_{1} - 6 \\, x_{2} - 8 \\, x_{3} + 176", "row1": "6 \\, x_{1} + 4 \\, x_{2} + 18 \\, x_{3}", "row2": "-2 \\, x_{1} - x_{2} - 5 \\, x_{3}", "row3": "-2 \\, x_{1} - 2 \\, x_{2} - 6 \\, x_{3}", "x1value": "17", "x2value": "16", "x3value": "0", "optimalsolution": "12"}, {"emptyregion": false, "Fa11": "\\frac{9}{10}", "Fa12": "\\frac{1}{4}", "Fa13": "\\frac{49}{20}", "Fa21": "\\frac{1}{10}", "Fa22": "-\\frac{1}{4}", "Fa23": "\\frac{11}{20}", "Fa31": "-\\frac{3}{10}", "Fa32": "\\frac{1}{4}", "Fa33": "-\\frac{3}{20}", "Fb1": "\\frac{39}{2}", "Fb2": "\\frac{1}{2}", "Fb3": "\\frac{3}{2}", "Fc1": "1", "Fc2": "0", "Fc3": "-1", "Fd": "-15", "x1": "t_3", "x2": "t_2", "x3": "x_3", "t1": "t_1", "t2": "x_2", "t3": "x_1", "a11": "5", "a12": "6", "a13": "5", "a21": "-2", "a22": "-6", "a23": "-3", "a31": "-5", "a32": "-5", "a33": "-2", "b1": "30", "b2": "-6", "b3": "-10", "c1": "5", "c2": "5", "c3": "1", "d": "-5", "objectivefunction": "5 \\, x_{1} + 5 \\, x_{2} + x_{3} + 5", "row1": "5 \\, x_{1} + 6 \\, x_{2} + 5 \\, x_{3}", "row2": "-2 \\, x_{1} - 6 \\, x_{2} - 3 \\, x_{3}", "row3": "-5 \\, x_{1} - 5 \\, x_{2} - 2 \\, x_{3}", "x1value": "\\frac{3}{2}", "x2value": "\\frac{1}{2}", "x3value": "0", "optimalsolution": "15"}], "__seed__": "0012"}}, {"seed": 13, "data": {"tasks": [{"emptyregion": true, "Fa11": "1", "Fa12": "1", "Fa13": "1", "Fa21": "2", "Fa22": "1", "Fa23": "-1", "Fa31": "1", "Fa32": "-2", "Fa33": "1", "Fb1": "-17", "Fb2": "17", "Fb3": "12", "Fc1": "-5", "Fc2": "1", "Fc3": "4", "Fd": "0", "x1": "x_1", "x2": "t_3", "x3": "t_2", "t1": "t_1", "t2": "x_3", "t3": "x_2", "a11": "9", "a12": "2", "a13": "3", "a21": "-5", "a22": "-1", "a23": "-2", "a31": "-3", "a32": "-1", "a33": "-1", "b1": "58", "b2": "-46", "b3": "-29", "c1": "18", "c2": "5", "c3": "9", "d": "213", "objectivefunction": "18 \\, x_{1} + 5 \\, x_{2} + 9 \\, x_{3} - 213", "row1": "9 \\, x_{1} + 2 \\, x_{2} + 3 \\, x_{3}", "row2": "-5 \\, x_{1} - x_{2} - 2 \\, x_{3}", "row3": "-3 \\, x_{1} - x_{2} - x_{3}", "x1value": "0", "x2value": "12", "x3value": "17", "optimalsolution": "0"}, {"emptyregion": false, "Fa11": "-\\frac{1}{4}", "Fa12": "\\frac{7}{2}", "Fa13": "-\\frac{17}{4}", "Fa21": "\\frac{1}{4}", "Fa22": "-\\frac{3}{2}", "Fa23": "\\frac{9}{4}", "Fa31": "-\\frac{1}{4}", "Fa32": "\\frac{1}{2}", "Fa33": "-\\frac{1}{4}", "Fb1": "\\frac{13}{2}", "Fb2": "\\frac{3}{2}", "Fb3": "\\frac{1}{2}", "Fc1": "-\\frac{1}{2}", "Fc2": "5", "Fc3": "-\\frac{23}{2}", "Fd": "-20", "x1": "t_3", "x2": "t_2", "x3": "x_3", "t1": "t_1", "t2": "x_2", "t3": "x_1", "a11": "2", "a12": "3", "a13": "2", "a21": "-1", "a22": "-1", "a23": "-2", "a31": "-6", "a32": "-2", "a33": "-3", "b1": "12", "b2": "-2", "b3": "-6", "c1": "2", "c2": "4", "c3": "-3", "d": "-13", "objectivefunction": "2 \\, x_{1} + 4 \\, x_{2} - 3 \\, x_{3} + 13", "row1": "2 \\, x_{1} + 3 \\, x_{2} + 2 \\, x_{3}", "row2": "-x_{1} - x_{2} - 2 \\, x_{3}", "row3": "-6 \\, x_{1} - 2 \\, x_{2} - 3 \\, x_{3}", "x1value": "\\frac{1}{2}", "x2value": "\\frac{3}{2}", "x3value": "0", "optimalsolution": "20"}], "__seed__": "0013"}}, {"seed": 14, "data": {"tasks": [{"emptyregion": false, "Fa11": "0", "Fa12": "\\frac{8}{3}", "Fa13": "\\frac{5}{3}", "Fa21": "\\frac{1}{3}", "Fa22": "\\frac{5}{9}", "Fa23": "-\\frac{4}{9}", "Fa31": "-\\frac{1}{3}", "Fa32": "\\frac{1}{9}", "Fa33": "\\frac{1}{9}", "Fb1": "20", "Fb2": "\\frac{4}{3}", "Fb3": "\\frac{2}{3}", "Fc1": "\\frac{4}{3}", "Fc2": "\\frac{20}{9}", "Fc3": "-\\frac{7}{9}", "Fd": "-\\frac{59}{3}", "x1": "t_3", "x2": "x_2", "x3": "t_2", "t1": "t_1", "t2": "x_3", "t3": "x_1", "a11": "5", "a12": "6", "a13": "5", "a21": "-3", "a22": "-2", "a23": "-3", "a31": "-4", "a32": "-1", "a33": "-1", "b1": "30", "b2": "-6", "b3": "-4", "c1": "3", "c2": "2", "c3": "-1", "d": "-19", "objectivefunction": "3 \\, x_{1} + 2 \\, x_{2} - x_{3} + 19", "row1": "5 \\, x_{1} + 6 \\, x_{2} + 5 \\, x_{3}", "row2": "-3 \\, x_{1} - 2 \\, x_{2} - 3 \\, x_{3}", "row3": "-4 \\, x_{1} - x_{2} - x_{3}", "x1value": "\\frac{2}{3}", "x2value": "0", "x3value": "\\frac{4}{3}", "optimalsolution": "\\frac{59}{3}"}, {"emptyregion": true, "Fa11": "1", "Fa12": "1", "Fa13": "1", "Fa21": "1", "Fa22": "1", "Fa23": "-2", "Fa31": "1", "Fa32": "-1", "Fa33": "1", "Fb1": "-14", "Fb2": "13", "Fb3": "20", "Fc1": "3", "Fc2": "5", "Fc3": "1", "Fd": "-11", "x1": "x_1", "x2": "t_3", "x3": "t_2", "t1": "t_1", "t2": "x_3", "t3": "x_2", "a11": "6", "a12": "3", "a13": "2", "a21": "-2", "a22": "-1", "a23": "-1", "a31": "-3", "a32": "-2", "a33": "-1", "b1": "72", "b2": "-33", "b3": "-53", "c1": "20", "c2": "11", "c3": "6", "d": "287", "objectivefunction": "20 \\, x_{1} + 11 \\, x_{2} + 6 \\, x_{3} - 287", "row1": "6 \\, x_{1} + 3 \\, x_{2} + 2 \\, x_{3}", "row2": "-2 \\, x_{1} - x_{2} - x_{3}", "row3": "-3 \\, x_{1} - 2 \\, x_{2} - x_{3}", "x1value": "0", "x2value": "20", "x3value": "13", "optimalsolution": "11"}], "__seed__": "0014"}}, {"seed": 15, "data": {"tasks": [{"emptyregion": true, "Fa11": "2", "Fa12": "2", "Fa13": "2", "Fa21": "-1", "Fa22": "1", "Fa23": "1", "Fa31": "\\frac{1}{2}", "Fa32": "1", "Fa33": "-1", "Fb1": "-38", "Fb2": "18", "Fb3": "12", "Fc1": "3", "Fc2": "-2", "Fc3": "5", "Fd": "-14", "x1": "t_2", "x2": "x_2", "x3": "t_3", "t1": "t_1", "t2": "x_1", "t3": "x_3", "a11": "6", "a12": "16", "a13": "8", "a21": "-2", "a22": "-4", "a23": "-2", "a31": "-1", "a32": "-3", "a33": "-2", "b1": "166", "b2": "-60", "b3": "-42", "c1": "11", "c2": "25", "c3": "16", "d": "376", "objectivefunction": "11 \\, x_{1} + 25 \\, x_{2} + 16 \\, x_{3} - 376", "row1": "6 \\, x_{1} + 16 \\, x_{2} + 8 \\, x_{3}", "row2": "-2 \\, x_{1} - 4 \\, x_{2} - 2 \\, x_{3}", "row3": "-x_{1} - 3 \\, x_{2} - 2 \\, x_{3}", "x1value": "18", "x2value": "0", "x3value": "12", "optimalsolution": "14"}, {"emptyregion": false, "Fa11": "\\frac{19}{10}", "Fa12": "\\frac{19}{10}", "Fa13": "\\frac{3}{10}", "Fa21": "-\\frac{2}{5}", "Fa22": "\\frac{3}{5}", "Fa23": "\\frac{1}{5}", "Fa31": "\\frac{1}{10}", "Fa32": "\\frac{1}{10}", "Fa33": "-\\frac{3}{10}", "Fb1": "\\frac{87}{5}", "Fb2": "\\frac{8}{5}", "Fb3": "\\frac{3}{5}", "Fc1": "\\frac{1}{10}", "Fc2": "-\\frac{9}{10}", "Fc3": "\\frac{7}{10}", "Fd": "-\\frac{12}{5}", "x1": "t_2", "x2": "x_2", "x3": "t_3", "t1": "t_1", "t2": "x_1", "t3": "x_3", "a11": "6", "a12": "6", "a13": "5", "a21": "-3", "a22": "-2", "a23": "-2", "a31": "-1", "a32": "-1", "a33": "-4", "b1": "30", "b2": "-6", "b3": "-4", "c1": "1", "c2": "0", "c3": "3", "d": "1", "objectivefunction": "x_{1} + 3 \\, x_{3} - 1", "row1": "6 \\, x_{1} + 6 \\, x_{2} + 5 \\, x_{3}", "row2": "-3 \\, x_{1} - 2 \\, x_{2} - 2 \\, x_{3}", "row3": "-x_{1} - x_{2} - 4 \\, x_{3}", "x1value": "\\frac{8}{5}", "x2value": "0", "x3value": "\\frac{3}{5}", "optimalsolution": "\\frac{12}{5}"}], "__seed__": "0015"}}, {"seed": 16, "data": {"tasks": [{"emptyregion": false, "Fa11": "\\frac{1}{3}", "Fa12": "\\frac{2}{9}", "Fa13": "-\\frac{7}{9}", "Fa21": "-\\frac{1}{3}", "Fa22": "\\frac{1}{9}", "Fa23": "\\frac{10}{9}", "Fa31": "\\frac{1}{3}", "Fa32": "-\\frac{4}{9}", "Fa33": "-\\frac{4}{9}", "Fb1": "\\frac{10}{3}", "Fb2": "\\frac{2}{3}", "Fb3": "\\frac{4}{3}", "Fc1": "\\frac{4}{3}", "Fc2": "-\\frac{10}{9}", "Fc3": "\\frac{17}{9}", "Fd": "-\\frac{17}{3}", "x1": "t_2", "x2": "t_3", "x3": "x_3", "t1": "t_1", "t2": "x_1", "t3": "x_2", "a11": "2", "a12": "1", "a13": "1", "a21": "-4", "a22": "-1", "a23": "-4", "a31": "-3", "a32": "-3", "a33": "-2", "b1": "6", "b2": "-4", "b3": "-6", "c1": "2", "c2": "-2", "c3": "5", "d": "-7", "objectivefunction": "2 \\, x_{1} - 2 \\, x_{2} + 5 \\, x_{3} + 7", "row1": "2 \\, x_{1} + x_{2} + x_{3}", "row2": "-4 \\, x_{1} - x_{2} - 4 \\, x_{3}", "row3": "-3 \\, x_{1} - 3 \\, x_{2} - 2 \\, x_{3}", "x1value": "\\frac{2}{3}", "x2value": "\\frac{4}{3}", "x3value": "0", "optimalsolution": "\\frac{17}{3}"}, {"emptyregion": true, "Fa11": "2", "Fa12": "4", "Fa13": "1", "Fa21": "\\frac{1}{2}", "Fa22": "2", "Fa23": "-1", "Fa31": "-1", "Fa32": "2", "Fa33": "1", "Fb1": "-40", "Fb2": "18", "Fb3": "18", "Fc1": "3", "Fc2": "-8", "Fc3": "1", "Fd": "-18", "x1": "t_3", "x2": "x_2", "x3": "t_2", "t1": "t_1", "t2": "x_3", "t3": "x_1", "a11": "5", "a12": "26", "a13": "6", "a21": "-1", "a22": "-6", "a23": "-2", "a31": "-2", "a32": "-8", "a33": "-2", "b1": "158", "b2": "-54", "b3": "-72", "c1": "7", "c2": "22", "c3": "8", "d": "252", "objectivefunction": "7 \\, x_{1} + 22 \\, x_{2} + 8 \\, x_{3} - 252", "row1": "5 \\, x_{1} + 26 \\, x_{2} + 6 \\, x_{3}", "row2": "-x_{1} - 6 \\, x_{2} - 2 \\, x_{3}", "row3": "-2 \\, x_{1} - 8 \\, x_{2} - 2 \\, x_{3}", "x1value": "18", "x2value": "0", "x3value": "18", "optimalsolution": "18"}], "__seed__": "0016"}}, {"seed": 17, "data": {"tasks": [{"emptyregion": true, "Fa11": "3", "Fa12": "1", "Fa13": "2", "Fa21": "1", "Fa22": "\\frac{1}{3}", "Fa23": "-\\frac{2}{3}", "Fa31": "1", "Fa32": "-\\frac{2}{3}", "Fa33": "\\frac{1}{3}", "Fb1": "-39", "Fb2": "13", "Fb3": "19", "Fc1": "6", "Fc2": "3", "Fc3": "3", "Fd": "-54", "x1": "x_1", "x2": "t_3", "x3": "t_2", "t1": "t_1", "t2": "x_3", "t3": "x_2", "a11": "12", "a12": "4", "a13": "5", "a21": "-3", "a22": "-1", "a23": "-2", "a31": "-3", "a32": "-2", "a33": "-1", "b1": "102", "b2": "-45", "b3": "-51", "c1": "24", "c2": "9", "c3": "9", "d": "234", "objectivefunction": "24 \\, x_{1} + 9 \\, x_{2} + 9 \\, x_{3} - 234", "row1": "12 \\, x_{1} + 4 \\, x_{2} + 5 \\, x_{3}", "row2": "-3 \\, x_{1} - x_{2} - 2 \\, x_{3}", "row3": "-3 \\, x_{1} - 2 \\, x_{2} - x_{3}", "x1value": "0", "x2value": "19", "x3value": "13", "optimalsolution": "54"}, {"emptyregion": false, "Fa11": "\\frac{2}{3}", "Fa12": "\\frac{11}{9}", "Fa13": "\\frac{14}{9}", "Fa21": "-\\frac{2}{3}", "Fa22": "\\frac{4}{9}", "Fa23": "\\frac{1}{9}", "Fa31": "\\frac{1}{3}", "Fa32": "\\frac{1}{9}", "Fa33": "-\\frac{2}{9}", "Fb1": "\\frac{58}{3}", "Fb2": "\\frac{2}{3}", "Fb3": "\\frac{2}{3}", "Fc1": "-1", "Fc2": "\\frac{14}{3}", "Fc3": "\\frac{2}{3}", "Fd": "-8", "x1": "t_2", "x2": "x_2", "x3": "t_3", "t1": "t_1", "t2": "x_1", "t3": "x_3", "a11": "6", "a12": "5", "a13": "10", "a21": "-2", "a22": "-1", "a23": "-1", "a31": "-3", "a32": "-2", "a33": "-6", "b1": "30", "b2": "-2", "b3": "-6", "c1": "0", "c2": "5", "c3": "3", "d": "-6", "objectivefunction": "5 \\, x_{2} + 3 \\, x_{3} + 6", "row1": "6 \\, x_{1} + 5 \\, x_{2} + 10 \\, x_{3}", "row2": "-2 \\, x_{1} - x_{2} - x_{3}", "row3": "-3 \\, x_{1} - 2 \\, x_{2} - 6 \\, x_{3}", "x1value": "\\frac{2}{3}", "x2value": "0", "x3value": "\\frac{2}{3}", "optimalsolution": "8"}], "__seed__": "0017"}}, {"seed": 18, "data": {"tasks": [{"emptyregion": true, "Fa11": "1", "Fa12": "4", "Fa13": "1", "Fa21": "1", "Fa22": "1", "Fa23": "-1", "Fa31": "-1", "Fa32": "1", "Fa33": "\\frac{1}{2}", "Fb1": "-36", "Fb2": "18", "Fb3": "12", "Fc1": "1", "Fc2": "6", "Fc3": "5", "Fd": "4", "x1": "t_3", "x2": "x_2", "x3": "t_2", "t1": "t_1", "t2": "x_3", "t3": "x_1", "a11": "4", "a12": "11", "a13": "3", "a21": "-2", "a22": "-4", "a23": "-2", "a31": "-2", "a32": "-3", "a33": "-1", "b1": "66", "b2": "-60", "b3": "-42", "c1": "12", "c2": "29", "c3": "11", "d": "346", "objectivefunction": "12 \\, x_{1} + 29 \\, x_{2} + 11 \\, x_{3} - 346", "row1": "4 \\, x_{1} + 11 \\, x_{2} + 3 \\, x_{3}", "row2": "-2 \\, x_{1} - 4 \\, x_{2} - 2 \\, x_{3}", "row3": "-2 \\, x_{1} - 3 \\, x_{2} - x_{3}", "x1value": "12", "x2value": "0", "x3value": "18", "optimalsolution": "-4"}, {"emptyregion": false, "Fa11": "\\frac{13}{16}", "Fa12": "\\frac{55}{32}", "Fa13": "\\frac{9}{32}", "Fa21": "-\\frac{3}{16}", "Fa22": "\\frac{15}{32}", "Fa23": "\\frac{1}{32}", "Fa31": "\\frac{1}{16}", "Fa32": "\\frac{3}{32}", "Fa33": "-\\frac{3}{32}", "Fb1": "\\frac{87}{4}", "Fb2": "\\frac{3}{4}", "Fb3": "\\frac{3}{4}", "Fc1": "-\\frac{19}{16}", "Fc2": "\\frac{223}{32}", "Fc3": "\\frac{17}{32}", "Fd": "-\\frac{33}{4}", "x1": "t_2", "x2": "x_2", "x3": "t_3", "t1": "t_1", "t2": "x_1", "t3": "x_3", "a11": "6", "a12": "5", "a13": "5", "a21": "-6", "a22": "-3", "a23": "-2", "a31": "-4", "a32": "-3", "a33": "-12", "b1": "30", "b2": "-6", "b3": "-12", "c1": "-5", "c2": "5", "c3": "4", "d": "-9", "objectivefunction": "-5 \\, x_{1} + 5 \\, x_{2} + 4 \\, x_{3} + 9", "row1": "6 \\, x_{1} + 5 \\, x_{2} + 5 \\, x_{3}", "row2": "-6 \\, x_{1} - 3 \\, x_{2} - 2 \\, x_{3}", "row3": "-4 \\, x_{1} - 3 \\, x_{2} - 12 \\, x_{3}", "x1value": "\\frac{3}{4}", "x2value": "0", "x3value": "\\frac{3}{4}", "optimalsolution": "\\frac{33}{4}"}], "__seed__": "0018"}}, {"seed": 19, "data": {"tasks": [{"emptyregion": true, "Fa11": "6", "Fa12": "2", "Fa13": "1", "Fa21": "1", "Fa22": "\\frac{1}{3}", "Fa23": "-\\frac{2}{3}", "Fa31": "1", "Fa32": "-\\frac{2}{3}", "Fa33": "\\frac{1}{3}", "Fb1": "-33", "Fb2": "17", "Fb3": "17", "Fc1": "6", "Fc2": "5", "Fc3": "-4", "Fd": "-42", "x1": "x_1", "x2": "t_3", "x3": "t_2", "t1": "t_1", "t2": "x_3", "t3": "x_2", "a11": "15", "a12": "5", "a13": "4", "a21": "-3", "a22": "-1", "a23": "-2", "a31": "-3", "a32": "-2", "a33": "-1", "b1": "120", "b2": "-51", "b3": "-51", "c1": "9", "c2": "6", "c3": "-3", "d": "9", "objectivefunction": "9 \\, x_{1} + 6 \\, x_{2} - 3 \\, x_{3} - 9", "row1": "15 \\, x_{1} + 5 \\, x_{2} + 4 \\, x_{3}", "row2": "-3 \\, x_{1} - x_{2} - 2 \\, x_{3}", "row3": "-3 \\, x_{1} - 2 \\, x_{2} - x_{3}", "x1value": "0", "x2value": "17", "x3value": "17", "optimalsolution": "42"}, {"emptyregion": false, "Fa11": "\\frac{1}{3}", "Fa12": "\\frac{2}{3}", "Fa13": "0", "Fa21": "\\frac{1}{18}", "Fa22": "-\\frac{5}{9}", "Fa23": "\\frac{5}{6}", "Fa31": "-\\frac{1}{9}", "Fa32": "\\frac{1}{9}", "Fa33": "\\frac{1}{3}", "Fb1": "\\frac{22}{3}", "Fb2": "\\frac{5}{9}", "Fb3": "\\frac{8}{9}", "Fc1": "\\frac{4}{9}", "Fc2": "\\frac{5}{9}", "Fc3": "-\\frac{19}{3}", "Fd": "-\\frac{122}{9}", "x1": "t_3", "x2": "t_2", "x3": "x_3", "t1": "t_1", "t2": "x_2", "t3": "x_1", "a11": "4", "a12": "2", "a13": "3", "a21": "-1", "a22": "-2", "a23": "-2", "a31": "-10", "a32": "-2", "a33": "-5", "b1": "12", "b2": "-2", "b3": "-10", "c1": "5", "c2": "2", "c3": "-3", "d": "-8", "objectivefunction": "5 \\, x_{1} + 2 \\, x_{2} - 3 \\, x_{3} + 8", "row1": "4 \\, x_{1} + 2 \\, x_{2} + 3 \\, x_{3}", "row2": "-x_{1} - 2 \\, x_{2} - 2 \\, x_{3}", "row3": "-10 \\, x_{1} - 2 \\, x_{2} - 5 \\, x_{3}", "x1value": "\\frac{8}{9}", "x2value": "\\frac{5}{9}", "x3value": "0", "optimalsolution": "\\frac{122}{9}"}], "__seed__": "0019"}}], "generated_on": "2025-08-21T16:05:11.719792+00:00"}